RHINOpy/LD90.py
RHINOpy/RHINO.py
RHINOpy/TM5.py
RHINOpy/__init__.py
RHINOpy/com.py
RHINOpy/config.py
RHINOpy/cs.py
RHINOpy/customs.py
RHINOpy/detect.py
RHINOpy/exceptions.py
RHINOpy/helpers.py
RHINOpy/structs.py
RHINOpy-0.0.2.dist-info/LICENSE
RHINOpy-0.0.2.dist-info/METADATA
RHINOpy-0.0.2.dist-info/WHEEL
RHINOpy-0.0.2.dist-info/top_level.txt
RHINOpy-0.0.2.dist-info/RECORD
