Metadata-Version: 2.1
Name: RHINOpy
Version: 0.0.2
Summary: Quicksample Test Package for SQLShack Demo
Author: Moritz Muellerschoen
Classifier: Programming Language :: Python :: 3
Classifier: License :: OSI Approved :: MIT License
Classifier: Operating System :: OS Independent
Requires-Python: >=3.8
License-File: LICENSE
Requires-Dist: numpy
Requires-Dist: scipy
Requires-Dist: techmanpy
Requires-Dist: asyncio
Requires-Dist: telnetlib3
Requires-Dist: paho-mqtt
Requires-Dist: opencv-contrib-python
